{
  "project_info": {
    "project_number": "1097261301084",
    "firebase_url": "https://mad-assignment-three-default-rtdb.europe-west1.firebasedatabase.app",
    "project_id": "mad-assignment-three",
    "storage_bucket": "mad-assignment-three.appspot.com"
  },
  "client": [
    {
      "client_info": {
        "mobilesdk_app_id": "1:1097261301084:android:6aa8b987675b5b4e385599",
        "android_client_info": {
          "package_name": "com.mobappdev.pricewatch"
        }
      },
      "oauth_client": [],
      "api_key": [
        {
          "current_key": "AIzaSyDlq4z2x4Yy9hKD3JvdvXG2Bq9b24RQizE"
        }
      ],
      "services": {
        "appinvite_service": {
          "other_platform_oauth_client": []
        }
      }
    }
  ],
  "configuration_version": "1"
}